topsis/__init__.py
topsis/main.py
Topsis_Mandar_102203163-1.0.dist-info/METADATA
Topsis_Mandar_102203163-1.0.dist-info/WHEEL
Topsis_Mandar_102203163-1.0.dist-info/entry_points.txt
Topsis_Mandar_102203163-1.0.dist-info/top_level.txt
Topsis_Mandar_102203163-1.0.dist-info/RECORD
