Metadata-Version: 2.2
Name: Topsis-Mandar-102203163
Version: 1.0
Summary: A Python Package which creates topsis rankings on the basis of performance scores
Home-page: https://github.com/mandarmgd/topsis
Author: Mandar
Author-email: mandargarud1811@gmail.com
Classifier: Programming Language :: Python :: 3
Classifier: License :: OSI Approved :: MIT License
Classifier: Operating System :: OS Independent
Requires-Python: >=3.6
Requires-Dist: numpy
Requires-Dist: pandas
Requires-Dist: scipy
Dynamic: author
Dynamic: author-email
Dynamic: classifier
Dynamic: description
Dynamic: description-content-type
Dynamic: home-page
Dynamic: requires-dist
Dynamic: requires-python
Dynamic: summary
